[
  {
    "category": "Cloud & Infrastructure",
    "items": ["AWS (EC2, S3, Lambda, RDS, DynamoDB, API Gateway, IAM, CloudFront, Step Functions, SNS, SQS, EventBridge, CloudWatch, ECS)", "AWS CDK", "Infrastructure as Code", "Linux (CLI)"]
  },
  {
    "category": "Backend Development",
    "items": ["Python", "REST APIs", "Microservices Architecture", "UNIX"]
  },
  {
    "category": "Databases",
    "items": ["DynamoDB", "PostgreSQL", "MySQL"]
  },
  {
    "category": "Tools & DevOps",
    "items": ["GitHub", "GitLab", "Postman", "DBeaver", "PyCharm", "IntelliJ IDEA", "VS Code", "Android Studio", "Arduino"]
  }
]
